mlxtend/__init__.py
mlxtend/_base/__init__.py
mlxtend/_base/_base_model.py
mlxtend/_base/_classifier.py
mlxtend/_base/_cluster.py
mlxtend/_base/_iterative_model.py
mlxtend/_base/_multiclass.py
mlxtend/_base/_multilayer.py
mlxtend/_base/_regressor.py
mlxtend/classifier/__init__.py
mlxtend/classifier/_base_classification.py
mlxtend/classifier/adaline.py
mlxtend/classifier/ensemble_vote.py
mlxtend/classifier/logistic_regression.py
mlxtend/classifier/multilayerperceptron.py
mlxtend/classifier/oner.py
mlxtend/classifier/perceptron.py
mlxtend/classifier/softmax_regression.py
mlxtend/classifier/stacking_classification.py
mlxtend/classifier/stacking_cv_classification.py
mlxtend/cluster/__init__.py
mlxtend/cluster/kmeans.py
mlxtend/data/__init__.py
mlxtend/data/autompg.py
mlxtend/data/boston_housing.py
mlxtend/data/iris.py
mlxtend/data/local_mnist.py
mlxtend/data/mnist.py
mlxtend/data/multiplexer.py
mlxtend/data/three_blobs.py
mlxtend/data/wine.py
mlxtend/data/data/autompg.csv.gz
mlxtend/data/data/boston_housing.csv
mlxtend/data/data/iris.csv.gz
mlxtend/data/data/mnist_5k.csv.gz
mlxtend/data/data/three_blobs.csv.gz
mlxtend/data/data/wine.csv
mlxtend/evaluate/__init__.py
mlxtend/evaluate/accuracy.py
mlxtend/evaluate/bias_variance_decomp.py
mlxtend/evaluate/bootstrap.py
mlxtend/evaluate/bootstrap_outofbag.py
mlxtend/evaluate/bootstrap_point632.py
mlxtend/evaluate/cochrans_q.py
mlxtend/evaluate/confusion_matrix.py
mlxtend/evaluate/counterfactual.py
mlxtend/evaluate/f_test.py
mlxtend/evaluate/feature_importance.py
mlxtend/evaluate/holdout.py
mlxtend/evaluate/lift_score.py
mlxtend/evaluate/mcnemar.py
mlxtend/evaluate/permutation.py
mlxtend/evaluate/proportion_difference.py
mlxtend/evaluate/scoring.py
mlxtend/evaluate/time_series.py
mlxtend/evaluate/ttest.py
mlxtend/externals/__init__.py
mlxtend/externals/adjust_text.py
mlxtend/externals/estimator_checks.py
mlxtend/externals/name_estimators.py
mlxtend/externals/signature_py27.py
mlxtend/externals/pyprind/__init__.py
mlxtend-0.23.3.dist-info/LICENSE-BSD3.txt
mlxtend-0.23.3.dist-info/LICENSE-CC-BY.txt
mlxtend-0.23.3.dist-info/METADATA
mlxtend-0.23.3.dist-info/WHEEL
mlxtend-0.23.3.dist-info/top_level.txt
mlxtend-0.23.3.dist-info/RECORD
