Metadata-Version: 2.1
Name: mlxtend
Version: 0.23.3
Summary: Machine Learning Library Extensions
Author-email: Sebastian Raschka <mail@sebastianraschka.com>
License: BSD 3-Clause
Project-URL: Homepage, https://github.com/rasbt/mlxtend
Project-URL: Documentation, https://rasbt.github.io/mlxtend
Project-URL: Repository, https://github.com/rasbt/mlxtend
Platform: any
Classifier: License :: OSI Approved :: BSD License
Classifier: Development Status :: 5 - Production/Stable
Classifier: Operating System :: Microsoft :: Windows
Classifier: Operating System :: POSIX
Classifier: Operating System :: Unix
Classifier: Operating System :: MacOS
Classifier: Programming Language :: Python :: 3.7
Classifier: Programming Language :: Python :: 3.8
Classifier: Programming Language :: Python :: 3.9
Classifier: Programming Language :: Python :: 3.10
Classifier: Programming Language :: Python :: 3.11
Classifier: Topic :: Scientific/Engineering
Classifier: Topic :: Scientific/Engineering :: Artificial Intelligence
Classifier: Topic :: Scientific/Engineering :: Information Analysis
Classifier: Topic :: Scientific/Engineering :: Image Recognition
License-File: LICENSE-BSD3.txt
License-File: LICENSE-CC-BY.txt
Requires-Dist: scipy>=1.2.1
Requires-Dist: numpy>=1.16.2
Requires-Dist: pandas>=0.24.2
Requires-Dist: scikit-learn>=1.3.1
Requires-Dist: matplotlib>=3.0.0
Requires-Dist: joblib>=0.13.2
Provides-Extra: testing
Requires-Dist: pytest; extra == "testing"
Provides-Extra: docs
Requires-Dist: mkdocs; extra == "docs"
Requires-Dist: python-markdown-math; extra == "docs"
Requires-Dist: mkdocs-bootswatch; extra == "docs"
Requires-Dist: nbconvert; extra == "docs"
